CHANGES.rst
MANIFEST.in
README.rst
setup.py
Products/__init__.py
Products.enablesettrace.egg-info/PKG-INFO
Products.enablesettrace.egg-info/SOURCES.txt
Products.enablesettrace.egg-info/dependency_links.txt
Products.enablesettrace.egg-info/namespace_packages.txt
Products.enablesettrace.egg-info/not-zip-safe
Products.enablesettrace.egg-info/requires.txt
Products.enablesettrace.egg-info/top_level.txt
Products/enablesettrace/__init__.py
Products/enablesettrace/monkeypatch.py
docs/LICENSE.txt